PyPgms/PyPgms.py
PyPgms/__init__.py
PyPgms-0.7.dist-info/LICENSE
PyPgms-0.7.dist-info/METADATA
PyPgms-0.7.dist-info/WHEEL
PyPgms-0.7.dist-info/top_level.txt
PyPgms-0.7.dist-info/RECORD
