Metadata-Version: 2.1
Name: PyPgms
Version: 0.7
Summary: Python Programs
Home-page: 
Author: Pyxd
Author-email: 
Project-URL: Bug Tracker, https://github.com/pypa/sampleproject/issues
Classifier: Programming Language :: Python :: 3
Classifier: License :: OSI Approved :: MIT License
Classifier: Operating System :: OS Independent
Requires-Python: >=3.6
License-File: LICENSE
Requires-Dist: requests
Requires-Dist: PyPDF2
Requires-Dist: openpyxl
